README.md
setup.py
NROBOT/__init__.py
NROBOT.egg-info/PKG-INFO
NROBOT.egg-info/SOURCES.txt
NROBOT.egg-info/dependency_links.txt
NROBOT.egg-info/requires.txt
NROBOT.egg-info/top_level.txt
bin/nrobot