Metadata-Version: 2.1
Name: NROBOT
Version: 0.1.1
Summary: NROBOT API library
Home-page: https://NROBOT.readthedocs.io/
Author: Nasir Ali
Author-email: nasiraliphy@gmail.com
License: MIT
Platform: UNKNOWN
Classifier: Intended Audience :: Developers
Classifier: License :: OSI Approved :: MIT License
Classifier: Programming Language :: Python
Classifier: Programming Language :: Python :: 3
Classifier: Programming Language :: Python :: 3.6
Classifier: Programming Language :: Python :: 3.7
Classifier: Programming Language :: Python :: 3.8
Classifier: Programming Language :: Python :: 3.9
Classifier: Operating System :: OS Independent
